fmla/__init__.py
fmla/__tests__/test_cli.py
fmla/__tests__/test_welcome.py
fmla/cli.py
fmla-0.0.2.dist-info/METADATA
fmla-0.0.2.dist-info/WHEEL
fmla-0.0.2.dist-info/entry_points.txt
fmla-0.0.2.dist-info/RECORD
