Metadata-Version: 2.1
Name: fmla
Version: 0.0.2
Summary: A Python package with CLI tools to help navigate Performance Improvement Plans (PIP) and Family Medical Leave Act (FMLA) situations
Author: Pipped Engineer
Requires-Python: >=3.10
Classifier: Programming Language :: Python :: 3
Classifier: Programming Language :: Python :: 3.10
Classifier: Programming Language :: Python :: 3.11
Classifier: Programming Language :: Python :: 3.12
